aisy_sca/Aisy.py
aisy_sca/AnalysisControls.py
aisy_sca/AnalysisDatabaseControls.py
aisy_sca/LeakageModelControls.py
aisy_sca/__init__.py
aisy_sca/analysis/HyperparameterSearchProcess.py
aisy_sca/analysis/MultiModel.py
aisy_sca/analysis/SingleModel.py
aisy_sca/analysis/SingleProcess.py
aisy_sca/analysis/__init__.py
aisy_sca/callbacks/CallbackControls.py
aisy_sca/callbacks/Callbacks.py
aisy_sca/callbacks/__init__.py
aisy_sca/crypto/__init__.py
aisy_sca/crypto/sca_aes_create_intermediates.py
aisy_sca/crypto/aes/__init__.py
aisy_sca/crypto/aes/aes128.py
aisy_sca/crypto/aes/intermediates_decrypt.py
aisy_sca/crypto/aes/intermediates_encrypt.py
aisy_sca/datasets/Dataset.py
aisy_sca/datasets/DatasetControls.py
aisy_sca/datasets/__init__.py
aisy_sca/metrics/SCAMetrics.py
aisy_sca/metrics/__init__.py
aisy_sca/optimization/Ensemble.py
aisy_sca/optimization/EnsembleControls.py
aisy_sca/optimization/HyperparameterSearch.py
aisy_sca/optimization/KerasCNNGrid.py
aisy_sca/optimization/KerasCNNRandom.py
aisy_sca/optimization/KerasMLPGrid.py
aisy_sca/optimization/KerasMLPRandom.py
aisy_sca/optimization/ProfilingAnalyzer.py
aisy_sca/optimization/RandomGridSearch.py
aisy_sca/optimization/__init__.py
aisy_sca/sca/Profiling.py
aisy_sca/sca/__init__.py
aisy_sca/utils/__init__.py
aisy_sca/utils/utils.py
tests/__init__.py
aisy_sca-0.2.7.dist-info/LICENSE
aisy_sca-0.2.7.dist-info/METADATA
aisy_sca-0.2.7.dist-info/WHEEL
aisy_sca-0.2.7.dist-info/top_level.txt
aisy_sca-0.2.7.dist-info/RECORD
