Metadata-Version: 2.1
Name: aisy-sca
Version: 0.2.7
Summary: Deep Learning-based Framework for Side Channel Analysis
Home-page: https://aisylab.github.io/AISY_docs/
Author: Guilherme Perin
Author-email: guilhermeperin7@gmail.com
License: UNKNOWN
Keywords: side-channel analysis deep learning profiled attacks
Platform: UNKNOWN
Classifier: Programming Language :: Python :: 3
Classifier: License :: OSI Approved :: MIT License
Classifier: Operating System :: OS Independent
License-File: LICENSE
